odoo/addons/website_crm_recaptcha/README.rst
odoo/addons/website_crm_recaptcha/__init__.py
odoo/addons/website_crm_recaptcha/__manifest__.py
odoo/addons/website_crm_recaptcha/hooks.py
odoo/addons/website_crm_recaptcha/data/ir_model_data.xml
odoo/addons/website_crm_recaptcha/i18n/hr.po
odoo/addons/website_crm_recaptcha/i18n/website_crm_recaptcha.pot
odoo/addons/website_crm_recaptcha/i18n/zh_CN.po
odoo/addons/website_crm_recaptcha/static/description/icon.png
odoo/addons/website_crm_recaptcha/views/website_crm_template.xml
odoo11_addon_website_crm_recaptcha-11.0.1.0.1.dist-info/METADATA
odoo11_addon_website_crm_recaptcha-11.0.1.0.1.dist-info/WHEEL
odoo11_addon_website_crm_recaptcha-11.0.1.0.1.dist-info/top_level.txt
odoo11_addon_website_crm_recaptcha-11.0.1.0.1.dist-info/RECORD
